hcls_imaging_ml_toolkit/__init__.py
hcls_imaging_ml_toolkit/caip.py
hcls_imaging_ml_toolkit/caip_test.py
hcls_imaging_ml_toolkit/dicom_builder.py
hcls_imaging_ml_toolkit/dicom_builder_test.py
hcls_imaging_ml_toolkit/dicom_json.py
hcls_imaging_ml_toolkit/dicom_json_test.py
hcls_imaging_ml_toolkit/dicom_path.py
hcls_imaging_ml_toolkit/dicom_path_test.py
hcls_imaging_ml_toolkit/dicom_web.py
hcls_imaging_ml_toolkit/dicom_web_test.py
hcls_imaging_ml_toolkit/exception.py
hcls_imaging_ml_toolkit/model_server.py
hcls_imaging_ml_toolkit/model_server_test.py
hcls_imaging_ml_toolkit/monitoring.py
hcls_imaging_ml_toolkit/publisher.py
hcls_imaging_ml_toolkit/pubsub_format.py
hcls_imaging_ml_toolkit/pubsub_format_test.py
hcls_imaging_ml_toolkit/pubsub_response.py
hcls_imaging_ml_toolkit/subscription.py
hcls_imaging_ml_toolkit/subscription_test.py
hcls_imaging_ml_toolkit/tag_values.py
hcls_imaging_ml_toolkit/tags.py
hcls_imaging_ml_toolkit/test_dicom_path_util.py
hcls_imaging_ml_toolkit/test_dwc_util.py
hcls_imaging_ml_toolkit/test_pubsub_util.py
hcls_imaging_ml_toolkit-0.1.dist-info/METADATA
hcls_imaging_ml_toolkit-0.1.dist-info/WHEEL
hcls_imaging_ml_toolkit-0.1.dist-info/top_level.txt
hcls_imaging_ml_toolkit-0.1.dist-info/RECORD
